pyplantsim/__init__.py
pyplantsim/call_cycle.py
pyplantsim/events.py
pyplantsim/exception.py
pyplantsim/licenses.py
pyplantsim/plantsim.py
pyplantsim/py.typed
pyplantsim/versions.py
pyplantsim/instance_handler/__init__.py
pyplantsim/instance_handler/exception.py
pyplantsim/instance_handler/instance_handler.py
pyplantsim/instance_handler/job.py
pyplantsim/sim_talk_scripts/activate_profiler.st
pyplantsim/sim_talk_scripts/exists_path.st
pyplantsim/sim_talk_scripts/get_call_cycles.st
pyplantsim/sim_talk_scripts/get_model_language.st
pyplantsim/sim_talk_scripts/get_table_column_data_type.st
pyplantsim/sim_talk_scripts/install_error_handler.st
pyplantsim/sim_talk_scripts/remove_error_handler.st
pyplantsim-0.4.5.dist-info/licenses/LICENSE
pyplantsim-0.4.5.dist-info/METADATA
pyplantsim-0.4.5.dist-info/WHEEL
pyplantsim-0.4.5.dist-info/top_level.txt
pyplantsim-0.4.5.dist-info/RECORD
