Metadata-Version: 2.4
Name: pyplantsim
Version: 0.4.5
Summary: A Python wrapper for Siemens Tecnomatix Plant Simulation COM Interface
Author-email: Luca Bernstiel <bernstiel@gmx.de>
License-Expression: MIT
Project-URL: Homepage, https://github.com/malun22/pyplantsim
Project-URL: Documentation, https://malun22.github.io/pyplantsim/
Project-URL: Repository, https://github.com/malun22/pyplantsim
Keywords: plant,siemens,simulation,COM
Requires-Python: >=3.13
License-File: LICENSE
Requires-Dist: loguru>=0.7.3
Requires-Dist: pywin32>=311; platform_system == "Windows"
Requires-Dist: win32_setctime>=1.2.0; platform_system == "Windows"
Requires-Dist: pandas>=2.3.2
Requires-Dist: psutil>=7.0.0
Requires-Dist: plantsimpath>=0.0.3
Requires-Dist: packaging>=25.0
Provides-Extra: dev
Requires-Dist: mypy; extra == "dev"
Requires-Dist: types-pywin32; extra == "dev"
Requires-Dist: pandas-stubs; extra == "dev"
Requires-Dist: types-psutil; extra == "dev"
Requires-Dist: loguru; extra == "dev"
Requires-Dist: plantsimpath; extra == "dev"
Requires-Dist: packaging; extra == "dev"
Provides-Extra: docs
Requires-Dist: sphinx; extra == "docs"
Requires-Dist: sphinx-autodoc-typehints; extra == "docs"
Requires-Dist: sphinx-rtd-theme; extra == "docs"
Dynamic: license-file
